dbnd_airflow/__init__.py
dbnd_airflow/compat.py
dbnd_airflow/entrypoint.py
dbnd_airflow/raw_constants.py
dbnd_airflow/utils.py
dbnd_airflow/export_plugin/__init__.py
dbnd_airflow/export_plugin/api_functions.py
dbnd_airflow/export_plugin/compat.py
dbnd_airflow/export_plugin/dag_operations.py
dbnd_airflow/export_plugin/datetime_utils.py
dbnd_airflow/export_plugin/helpers.py
dbnd_airflow/export_plugin/metrics.py
dbnd_airflow/export_plugin/models.py
dbnd_airflow/export_plugin/queries.py
dbnd_airflow/export_plugin/smart_dagbag.py
dbnd_airflow/export_plugin/utils.py
dbnd_airflow/testing/__init__.py
dbnd_airflow/testing/airflow_config.py
dbnd_airflow/testing/testing_shims.py
dbnd_airflow/testing/unittest_env.py
dbnd_airflow/tracking/__init__.py
dbnd_airflow/tracking/airflow_connections.py
dbnd_airflow/tracking/airflow_patching.py
dbnd_airflow/tracking/config.py
dbnd_airflow/tracking/dbnd_airflow_conf.py
dbnd_airflow/tracking/dbnd_airflow_handler.py
dbnd_airflow/tracking/dbnd_dag_tracking.py
dbnd_airflow/tracking/dbnd_spark_conf.py
dbnd_airflow/tracking/execute_tracking.py
dbnd_airflow/tracking/fakes.py
dbnd_airflow/tracking/operator_helpers.py
dbnd_airflow/tracking/wrap_operators.py
dbnd_airflow-1.0.30.1.dist-info/LICENSE
dbnd_airflow-1.0.30.1.dist-info/METADATA
dbnd_airflow-1.0.30.1.dist-info/WHEEL
dbnd_airflow-1.0.30.1.dist-info/top_level.txt
dbnd_airflow-1.0.30.1.dist-info/RECORD
